{
  "aor": 0.003965547445255475,
  "aqi": 0.006054781897810219,
  "bids_meta": {
    "EchoTime": 0.027,
    "FlipAngle": 90,
    "MagneticFieldStrength": 3,
    "ManufacturersModelName": "Tim TRIO",
    "RepetitionTime": 2.5,
    "TaskName": "letter 1-back task",
    "dataset": "ds000115",
    "modality": "bold",
    "subject_id": "44",
    "task_id": "letter1backtask"
  },
  "dummy_trs": 0,
  "dvars_nstd": 17.948121582500004,
  "dvars_std": 1.2813669552205882,
  "dvars_vstd": 1.0198920958088231,
  "efc": 0.42863752845001035,
  "fber": 17665.884765625,
  "fd_mean": 0.14836331644625425,
  "fd_num": 29,
  "fd_perc": 21.16788321167883,
  "fwhm_avg": 1.730124932521391,
  "fwhm_x": 1.565635,
  "fwhm_y": 1.926585,
  "fwhm_z": 1.698154797564173,
  "gcor": 0.0227892,
  "gsr_x": -0.028777344152331352,
  "gsr_y": 0.007243548519909382,
  "provenance": {
    "md5sum": "d3b1131f8e88d6dec70c9bb71836a80a",
    "settings": {
      "fd_thres": 0.2,
      "testing": false
    },
    "software": "mriqc",
    "version": "21.0.0rc2",
    "webapi_port": null,
    "webapi_url": "https://mriqc.nimh.nih.gov/api/v1"
  },
  "size_t": 137,
  "size_x": 64,
  "size_y": 64,
  "size_z": 36,
  "snr": 7.4063030125662666,
  "spacing_tr": 2.5,
  "spacing_x": 4.0,
  "spacing_y": 4.0,
  "spacing_z": 4.000000476837158,
  "summary_bg_k": 18.444428418954907,
  "summary_bg_mad": 3.971642699949104,
  "summary_bg_mean": 31.700315475463867,
  "summary_bg_median": 5.802919864654541,
  "summary_bg_n": 102386.0,
  "summary_bg_p05": 2.3740875720977783,
  "summary_bg_p95": 184.05656814575195,
  "summary_bg_stdv": 73.34124755859375,
  "summary_fg_k": 2.197398885657588,
  "summary_fg_mad": 97.93830092710706,
  "summary_fg_mean": 784.3845825195312,
  "summary_fg_median": 780.5949096679688,
  "summary_fg_n": 16644.0,
  "summary_fg_p05": 631.6302734375,
  "summary_fg_p95": 951.4565521240235,
  "summary_fg_stdv": 105.39286041259766,
  "tsnr": 83.43449531821534
}