{
  "aor": 0.009041605839416059,
  "aqi": 0.0083405398540146,
  "bids_meta": {
    "EchoTime": 0.027,
    "FlipAngle": 90,
    "MagneticFieldStrength": 3,
    "ManufacturersModelName": "Tim TRIO",
    "RepetitionTime": 2.5,
    "TaskName": "letter 1-back task",
    "dataset": "ds000115",
    "modality": "bold",
    "subject_id": "05",
    "task_id": "letter1backtask"
  },
  "dummy_trs": 0,
  "dvars_nstd": 24.425131959191184,
  "dvars_std": 1.395014516911764,
  "dvars_vstd": 1.0608866502941179,
  "efc": 0.37413622538616687,
  "fber": 26664.234375,
  "fd_mean": 0.19181318696601832,
  "fd_num": 31,
  "fd_perc": 22.62773722627737,
  "fwhm_avg": 1.5898916979626334,
  "fwhm_x": 1.4612125,
  "fwhm_y": 1.733285,
  "fwhm_z": 1.575177593887901,
  "gcor": 0.0388079,
  "gsr_x": -0.027910606935620308,
  "gsr_y": 0.00534737017005682,
  "provenance": {
    "md5sum": "b55b902416ba882e133390284ac49aa2",
    "settings": {
      "fd_thres": 0.2,
      "testing": false
    },
    "software": "mriqc",
    "version": "21.0.0rc2",
    "webapi_port": null,
    "webapi_url": "https://mriqc.nimh.nih.gov/api/v1"
  },
  "size_t": 137,
  "size_x": 64,
  "size_y": 64,
  "size_z": 36,
  "snr": 8.38522263532487,
  "spacing_tr": 2.5,
  "spacing_x": 4.0,
  "spacing_y": 4.0,
  "spacing_z": 3.999999761581421,
  "summary_bg_k": 45.68516821324757,
  "summary_bg_mad": 2.034519924288979,
  "summary_bg_mean": 12.307973861694336,
  "summary_bg_median": 3.1824817657470703,
  "summary_bg_n": 106384.0,
  "summary_bg_p05": 1.4744524955749512,
  "summary_bg_p95": 50.69744491577129,
  "summary_bg_stdv": 29.13376235961914,
  "summary_fg_k": 1.707387623410038,
  "summary_fg_mad": 56.387591007565334,
  "summary_fg_mean": 523.7380981445312,
  "summary_fg_median": 519.6824951171875,
  "summary_fg_n": 13968.0,
  "summary_fg_p05": 433.70619506835936,
  "summary_fg_p95": 627.0547332763672,
  "summary_fg_stdv": 61.97377395629883,
  "tsnr": 77.07822671916801
}