{
  "aor": 0.014353235294117648,
  "aqi": 0.022289515000000003,
  "bids_meta": {
    "EchoTime": 0.027,
    "FlipAngle": 90,
    "MagneticFieldStrength": 3,
    "ManufacturersModelName": "Tim TRIO",
    "RepetitionTime": 2.5,
    "TaskName": "letter 2-back task",
    "dataset": "ds000115",
    "modality": "bold",
    "subject_id": "31",
    "task_id": "letter2backtask"
  },
  "dummy_trs": 1,
  "dvars_nstd": 29.08617628577777,
  "dvars_std": 1.1511830549629631,
  "dvars_vstd": 0.9270344179259259,
  "efc": 0.4244886383865887,
  "fber": 25580.609375,
  "fd_mean": 0.45483161873548955,
  "fd_num": 98,
  "fd_perc": 72.05882352941177,
  "fwhm_avg": 1.6628153904345444,
  "fwhm_x": 1.5241925,
  "fwhm_y": 1.8266525,
  "fwhm_z": 1.6376011713036331,
  "gcor": 0.0454475,
  "gsr_x": -0.03435475751757622,
  "gsr_y": 0.017507454380393028,
  "provenance": {
    "md5sum": "0d4bebf2f65117043991d8c6e58a219b",
    "settings": {
      "fd_thres": 0.2,
      "testing": false
    },
    "software": "mriqc",
    "version": "21.0.0rc2",
    "webapi_port": null,
    "webapi_url": "https://mriqc.nimh.nih.gov/api/v1"
  },
  "size_t": 136,
  "size_x": 64,
  "size_y": 64,
  "size_z": 36,
  "snr": 7.992042587034125,
  "spacing_tr": 2.5,
  "spacing_x": 4.0,
  "spacing_y": 4.0,
  "spacing_z": 3.999997138977051,
  "summary_bg_k": 25.529360901070692,
  "summary_bg_mad": 2.8016825077724072,
  "summary_bg_mean": 21.269676208496094,
  "summary_bg_median": 4.169117450714111,
  "summary_bg_n": 100424.0,
  "summary_bg_p05": 1.720588207244873,
  "summary_bg_p95": 107.9632339477539,
  "summary_bg_stdv": 50.4422492980957,
  "summary_fg_k": 2.245257618814211,
  "summary_fg_mad": 76.5502436787483,
  "summary_fg_mean": 676.26611328125,
  "summary_fg_median": 669.4007568359375,
  "summary_fg_n": 18180.0,
  "summary_fg_p05": 555.7198455810546,
  "summary_fg_p95": 818.1885864257811,
  "summary_fg_stdv": 83.756103515625,
  "tsnr": 44.321334767038934
}